flask_chameleon/__init__.py
flask_chameleon-0.0.1.dist-info/LICENSE
flask_chameleon-0.0.1.dist-info/METADATA
flask_chameleon-0.0.1.dist-info/WHEEL
flask_chameleon-0.0.1.dist-info/top_level.txt
flask_chameleon-0.0.1.dist-info/RECORD
